poet/__init__.py
poet/poet.py
poet_estimator-0.1.dist-info/LICENSE
poet_estimator-0.1.dist-info/METADATA
poet_estimator-0.1.dist-info/WHEEL
poet_estimator-0.1.dist-info/top_level.txt
poet_estimator-0.1.dist-info/RECORD
