Metadata-Version: 2.1
Name: poet-estimator
Version: 0.1
Summary: Python Implementation for Large Covariance Estimation by Thresholding Principal Orthogonal Complements
Home-page: https://github.com/brucewuquant/POET
Author: Dizhou Wu
Author-email: dizhouwubruce@outlook.com
License: UNKNOWN
Platform: UNKNOWN
Classifier: Programming Language :: Python :: 3
Classifier: License :: OSI Approved :: Apache Software License
Classifier: Operating System :: OS Independent
Requires-Dist: scipy (>=1.5.1)
Requires-Dist: numpy (>=1.19.0)
